{
  "cli": {
    "version": ">= 12.0.0",
    "appVersionSource": "remote"
  },
  "build": {
    "development": {
      "developmentClient": true,
      "distribution": "internal",
      "env": {
        "EXPO_PUBLIC_API_URL": "http://localhost:5000"
      }
    },
    "preview": {
      "distribution": "internal",
      "ios": {
        "simulator": false
      },
      "env": {
        "EXPO_PUBLIC_API_URL": "https://api-staging.vor-platform.com"
      }
    },
    "production": {
      "autoIncrement": true,
      "env": {
        "EXPO_PUBLIC_API_URL": "https://api.vor-platform.com"
      }
    }
  },
  "submit": {
    "production": {
      "ios": {
        "appleId": "your-apple-id@example.com",
        "ascAppId": "1234567890",
        "appleTeamId": "YOUR_TEAM_ID"
      },
      "android": {
        "serviceAccountKeyPath": "./google-services-key.json",
        "track": "internal"
      }
    }
  }
}
